MProcs/__init__.py
MProcs/scripts/MProcs.py
MProcs/scripts/__init__.py
mprocs-8.4.dist-info/licenses/LICENSE
mprocs-8.4.dist-info/METADATA
mprocs-8.4.dist-info/WHEEL
mprocs-8.4.dist-info/entry_points.txt
mprocs-8.4.dist-info/top_level.txt
mprocs-8.4.dist-info/RECORD
