Metadata-Version: 2.4
Name: MProcs
Version: 8.4
Summary: A Life program by tderk, originally LPro.py and Destiny [2024]
Author-email: tderk <usvu.tech@gmail.com>
License: Copyright (c) 2018 The Python Packaging Authority
Keywords: life,hack,destiny,meta,program
Classifier: Programming Language :: Python :: 3
Classifier: License :: OSI Approved :: MIT License
Classifier: Operating System :: OS Independent
Requires-Python: >=3.8
License-File: LICENSE
Dynamic: license-file
